par_coordinates/__init__.py
par_coordinates/get_results.py
par_coordinates/plot.py
par_coordinates-0.3.dist-info/METADATA
par_coordinates-0.3.dist-info/WHEEL
par_coordinates-0.3.dist-info/top_level.txt
par_coordinates-0.3.dist-info/RECORD
