Metadata-Version: 2.1
Name: par-coordinates
Version: 0.3
Summary: Create parallel coordinates plots of the hyperparameter search
Home-page: https://github.com/tommaso-ferracci/Parallel_Coordinates_Plot
Author: Tommaso Ferracci
License: MIT
Project-URL: Documentation, https://tommaso-ferracci.github.io/Parallel_Coordinates_Plot/index.html
Project-URL: Source, https://github.com/tommaso-ferracci/Parallel_Coordinates_Plots
Keywords: parallel coordinates,parallel-coordinates,machine learning,deep learning,hyperparameter,visualization,plot
Requires-Dist: numpy >=1.26.4
Requires-Dist: matplotlib >=3.8.3
Requires-Dist: pandas >=2.2.1
